LICENSE
README.md
setup.py
liquicomun/__init__.py
liquicomun.egg-info/PKG-INFO
liquicomun.egg-info/SOURCES.txt
liquicomun.egg-info/dependency_links.txt
liquicomun.egg-info/requires.txt
liquicomun.egg-info/top_level.txt
liquicomun/datetime/__init__.py
liquicomun/datetime/season.py
liquicomun/datetime/timezone.py
liquicomun/formats/__init__.py
liquicomun/formats/component.py
liquicomun/formats/perdidas.py
liquicomun/formats/precios.py
liquicomun/formats/ree.py