Metadata-Version: 2.1
Name: liquicomun
Version: 0.4.4
Summary: Interact with REE liquicomun files
Home-page: https://github.com/gisce/liquicomun
Author: GISCE-TI, S.L.
Author-email: devel@gisce.net
License: MIT
Platform: UNKNOWN
